terraincache/__init__.py
terraincache/cli.py
terraincache/terraincache.py
terraincache-0.0.1.dist-info/LICENSE.txt
terraincache-0.0.1.dist-info/METADATA
terraincache-0.0.1.dist-info/WHEEL
terraincache-0.0.1.dist-info/entry_points.txt
terraincache-0.0.1.dist-info/top_level.txt
terraincache-0.0.1.dist-info/RECORD
