Metadata-Version: 2.1
Name: terraincache
Version: 0.0.1
Summary: Basic tool for downloading and merging mapzen terrain tile geotiffs from AWS
Home-page: https://github.com/smnorris/terraincache
Author: Simon Norris
Author-email: snorris@hillcrestgeo.ca
License: MIT
Keywords: terrain-tiles mapzen aws terrain dem s3 geotiff
Platform: UNKNOWN
Classifier: Development Status :: 3 - Alpha
Classifier: Intended Audience :: Developers
Classifier: License :: OSI Approved :: MIT License
Classifier: Operating System :: OS Independent
Classifier: Programming Language :: Python :: 3.6
Classifier: Programming Language :: Python :: 3.7
Classifier: Programming Language :: Python :: 3.8
Provides-Extra: test
